pymodalib/Platform.py
pymodalib/__init__.py
pymodalib/__main__.py
pymodalib/matlab_runtime.py
pymodalib/matlab_utils.py
pymodalib/algorithms/__init__.py
pymodalib/algorithms/bayesian.py
pymodalib/algorithms/coherence.py
pymodalib/algorithms/group_coherence.py
pymodalib/algorithms/harmonics.py
pymodalib/algorithms/preprocessing.py
pymodalib/algorithms/ridge_extraction.py
pymodalib/algorithms/signals.py
pymodalib/algorithms/surrogates.py
pymodalib/algorithms/wavelet.py
pymodalib/algorithms/windowed_fourier.py
pymodalib/implementations/__init__.py
pymodalib/implementations/matlab/__init__.py
pymodalib/implementations/matlab/bayesian.py
pymodalib/implementations/matlab/ridge_extraction.py
pymodalib/implementations/matlab/windowed_fourier.py
pymodalib/implementations/matlab/wavelet/__init__.py
pymodalib/implementations/matlab/wavelet/wavelet_transform.py
pymodalib/implementations/python/__init__.py
pymodalib/implementations/python/matlab_compat.py
pymodalib/implementations/python/bayesian/__init__.py
pymodalib/implementations/python/coherence/__init__.py
pymodalib/implementations/python/coherence/group_coherence.py
pymodalib/implementations/python/filtering/__init__.py
pymodalib/implementations/python/harmonics/__init__.py
pymodalib/implementations/python/harmonics/aaft4.py
pymodalib/implementations/python/harmonics/harmonics.py
pymodalib/implementations/python/signals/__init__.py
pymodalib/implementations/python/signals/preprocessing.py
pymodalib/implementations/python/wavelet/__init__.py
pymodalib/implementations/python/wavelet/wavelet_transform.py
pymodalib/plotting/__init__.py
pymodalib/plotting/colormap.mat
pymodalib/utils/Platform.py
pymodalib/utils/__init__.py
pymodalib/utils/cache.py
pymodalib/utils/chunks.py
pymodalib/utils/colormap.mat
pymodalib/utils/decorators.py
pymodalib/utils/matlab.py
pymodalib/utils/matlab_runtime.py
pymodalib/utils/parameters.py
pymodalib/utils/plotting.py
PyMODAlib-0.11.3b1.dist-info/LICENSE
PyMODAlib-0.11.3b1.dist-info/METADATA
PyMODAlib-0.11.3b1.dist-info/WHEEL
PyMODAlib-0.11.3b1.dist-info/top_level.txt
PyMODAlib-0.11.3b1.dist-info/RECORD
