Metadata-Version: 2.1
Name: PyMODAlib
Version: 0.11.3b1
Summary: Library providing Python implementations of MODA's algorithms.
Home-page: https://github.com/luphysics/PyMODAlib
Author: Lancaster University Physics
License: UNKNOWN
Project-URL: Source, https://github.com/luphysics/PyMODAlib
Keywords: moda pymoda wavelet-transform time-frequency-analysis
Platform: UNKNOWN
Classifier: Development Status :: 4 - Beta
Classifier: Intended Audience :: Developers
Classifier: License :: OSI Approved :: GNU General Public License v3 (GPLv3)
Classifier: Programming Language :: Python :: 3.6
Classifier: Programming Language :: Python :: 3.7
Classifier: Programming Language :: Python :: 3.8
Requires-Python: >=3.6
Requires-Dist: AsyncProcessScheduler (>=0.5.0b1)
Requires-Dist: chdir (>=1.0.0)
Requires-Dist: numpy (>=1.18.1)
Requires-Dist: scipy (>=1.4.1)
Requires-Dist: matplotlib (>=3.1.1)
